[
    {
        "id": 1,
        "image":
          "https://image.wanted.co.kr/optimize?src=https%3A%2F%2Fstatic.wanted.co.kr%2Fimages%2Fcompany%2F4%2Fyikyilr7bq6iypte__1080_790.jpg&w=1000&q=75",
        "title": "전략기획",
        "company": "아이엔지스토리",
        "site": "서울 한국",
        "money": "채용보상금 1,000,000원"
      },
      {
        "id": 2,
        "image":
          "https://image.wanted.co.kr/optimize?src=https%3A%2F%2Fstatic.wanted.co.kr%2Fimages%2Fcompany%2F4%2Ftnrcn43zjlpznjww__1080_790.jpg&w=1000&q=75",
        "title": "경영관리 (지원)",
        "company": "포항",
        "site": "서울 한국",
        "money": "채용보상금 1,000,000원"
      },
      {
        "id": 3,
        "image":
          "https://image.wanted.co.kr/optimize?src=https%3A%2F%2Fstatic.wanted.co.kr%2Fimages%2Fcompany%2F137%2Fncpb1pbv6mpl3a3x__1080_790.jpg&w=1000&q=75",
        "title": "HQ 경영관리팀 경영관리",
        "company": "에프엔스엔",
        "site": "서울 한국",
        "money": "채용보상금 1,000,000원"
      },
      {
        "id": 4,
        "image":
          "https://image.wanted.co.kr/optimize?src=https%3A%2F%2Fstatic.wanted.co.kr%2Fimages%2Fcompany%2F137%2Fw733fyzmucxvyuxm__1080_790.jpg&w=1000&q=75",
        "title": "공시 담당자",
        "company": "이스트소프트",
        "site": "서울 한국",
        "money": "채용보상금 1,000,000원"
      },
      {
        "id": 5,
        "image":
          "https://image.wanted.co.kr/optimize?src=https%3A%2F%2Fstatic.wanted.co.kr%2Fimages%2Fcompany%2F137%2Fybdlaw6ubrakrkcj__1080_790.jpg&w=1000&q=75",
        "title": "글로벌 커머스 기획",
        "company": "매드스퀘어",
        "site": "서울 한국",
        "money": "채용보상금 1,000,000원"
      },
      {
        "id": 6,
        "image":
          "https://image.wanted.co.kr/optimize?src=https%3A%2F%2Fstatic.wanted.co.kr%2Fimages%2Fcompany%2F137%2Fahndrwxcbupfdi3w__1080_790.jpg&w=1000&q=75",
        "title": "재무기획",
        "company": "쿠팡",
        "site": "서울 한국",
        "money": "채용보상금 1,000,000원"
      },
      {
        "id": 7,
        "image":
          "https://image.wanted.co.kr/optimize?src=https%3A%2F%2Fstatic.wanted.co.kr%2Fimages%2Fcompany%2F137%2F16ohsl8ldhkkhcno__1080_790.jpg&w=1000&q=75",
        "title": "경영관리",
        "company": "세어하우스우주",
        "site": "서울 한국",
        "money": "채용보상금 1,000,000원"
      },
      {
        "id": 8,
        "image":
          "https://image.wanted.co.kr/optimize?src=https%3A%2F%2Fstatic.wanted.co.kr%2Fimages%2Fcompany%2F137%2Fag49vpapvp7kng0f__1080_790.jpg&w=1000&q=75",
        "title": "서비스 운영 매니저",
        "company": "원티드랩",
        "site": "서울 한국",
        "money": "채용보상금 1,000,000원"
      },
      {
        "id": 9,
        "image":
          "https://image.wanted.co.kr/optimize?src=https%3A%2F%2Fstatic.wanted.co.kr%2Fimages%2Fcompany%2F137%2Ffctk9zbz2rb1upnj__1080_790.jpg&w=1000&q=75",
        "title": "네트워크 광고 운영 매니저",
        "company": "버즈빌",
        "site": "서울 한국",
        "money": "채용보상금 1,000,000원"
      },
      {
        "id": 10,
        "image":
          "https://image.wanted.co.kr/optimize?src=https%3A%2F%2Fstatic.wanted.co.kr%2Fimages%2Fcompany%2F137%2Fdfoka2yk4aqg46zy__1080_790.jpg&w=1000&q=75",
        "title": "파이낸스 매니저",
        "company": "굿닥",
        "site": "서울 한국",
        "money": "채용보상금 1,000,000원"
      },
      {
        "id": 11,
        "image":
          "https://image.wanted.co.kr/optimize?src=https%3A%2F%2Fstatic.wanted.co.kr%2Fimages%2Fcompany%2F137%2Fqpbivz9ihqtmm0vo__1080_790.jpg&w=1000&q=75",
        "title": "서비스운영 매니저",
        "company": "엠비티",
        "site": "서울 한국",
        "money": "채용보상금 1,000,000원"
      },
      {
        "id": 12,
        "image":
          "https://image.wanted.co.kr/optimize?src=https%3A%2F%2Fstatic.wanted.co.kr%2Fimages%2Fcompany%2F15%2F28xctz9hah8ba7q4__1080_790.jpg&w=1000&q=75",
        "title": "항공 운영 매니저",
        "company": "마이리얼트립",
        "site": "서울 한국",
        "money": "채용보상금 1,000,000원"
      }
]